{
    "version": 2,
    "settings": {
        "layout": {
            "contentSize": "840px",
            "wideSize": "1100px"
        },
        "color": {
            "palette": [
                {
                    "slug": "foreground",
                    "color": "#000000",
                    "name": "Foreground"
                },
                {
                    "slug": "background",
                    "color": "#ffffff",
                    "name": "Background"
                },
                {
                    "slug": "primary",
                    "color": "#1a4548",
                    "name": "Primary"
                },
                {
                    "slug": "secondary",
                    "color": "#ffe2c7",
                    "name": "Secondary"
                },
                {
                    "slug": "tertiary",
                    "color": "#F6F6F6",
                    "name": "Tertiary"
                }
            ] 
        },
        "typography": {
			"dropCap": false,
			"fontFamilies": [
				{
					"fontFamily": "\"Source Sans Pro\", sans-serif",
					"name": "Source Sans Pro",
					"slug": "source-sans-pro"
				}
			],
			"fontSizes": [
				{
					"size": "1rem",
					"slug": "small"
				},
				{
					"size": "1.125rem",
					"slug": "medium"
				},
				{
					"size": "1.75rem",
					"slug": "large"
				},
				{
					"size": "clamp(1.75rem, 3vw, 2.25rem)",
					"slug": "x-large"
				}
			]
		}
    },
    "themesettings":{
        "version" : "1.0.0",
        "prefix" : "kitely", 
        "contact": {
            "phone": "331-240-9155",
            "email": "ben.toth@kitelytech.com",
            "countrycode": "1",
            "social": [
                {"facebook": "https://www.facebook.com/kitelytech/"},
                {"twitter": "https://twitter.com/kitelytech"},
                {"linkedin": "https://www.linkedin.com/company/kitelytech/"},
                {"instagram": "https://www.instagram.com/kitelytech/"}
            ],
            "locations":[
                {"name": "CHICAGO", "phone":"331-240-9155", "email":null},
                {"name": "ATLANTA", "phone":"678-992-5332", "email":null},
                {"name": "AUSTIN", "phone":"512.895.9552", "email":null},
                {"name": "DETROIT", "phone":"313.449.8442", "email": null},
                {"name": "CHARLOTTE", "phone":"980.288.5559", "email":null},
                {"name": "NEW YORK", "phone":"917.745.5357", "email":null},
                {"name": "PHOENIX", "phone":"602.325.2707", "email":null},
                {"name": "MIAMI", "phone":"954.228.9921", "email":null}
            ]
        }

    }
}